resettabletimer/__init__.py
resettabletimer/_faketimer.py
resettabletimer/_resettabletimer.py
resettabletimer/_version.py
resettabletimer-1.0.0.dist-info/LICENSE
resettabletimer-1.0.0.dist-info/METADATA
resettabletimer-1.0.0.dist-info/WHEEL
resettabletimer-1.0.0.dist-info/top_level.txt
resettabletimer-1.0.0.dist-info/RECORD
