Metadata-Version: 2.1
Name: resettabletimer
Version: 1.0.0
Summary: Wrapper for threading.Timer to allow resetting
Home-page: https://github.com/kangasta/resettabletimer
Author: Toni Kangas
License: UNKNOWN
Platform: UNKNOWN
Classifier: Programming Language :: Python :: 3
Classifier: License :: OSI Approved :: MIT License
Classifier: Operating System :: OS Independent
License-File: LICENSE
